hypothesis_regex.py
hypothesis_regex-0.3.1.dist-info/DESCRIPTION.rst
hypothesis_regex-0.3.1.dist-info/METADATA
hypothesis_regex-0.3.1.dist-info/RECORD
hypothesis_regex-0.3.1.dist-info/WHEEL
hypothesis_regex-0.3.1.dist-info/metadata.json
hypothesis_regex-0.3.1.dist-info/top_level.txt
