Metadata-Version: 2.0
Name: hypothesis-regex
Version: 0.3.1
Summary: Hypothesis extension to allow generating strings based on regex
Home-page: https://github.com/maximkulkin/hypothesis-regex
Author: Maxim Kulkin
Author-email: maxim.kulkin@gmail.com
License: MIT
Keywords: hypothesis,regex
Platform: UNKNOWN
Classifier: Development Status :: 4 - Beta
Classifier: Intended Audience :: Developers
Classifier: License :: OSI Approved :: MIT License
Classifier: Programming Language :: Python :: 2
Classifier: Programming Language :: Python :: 2.7
Classifier: Programming Language :: Python :: 3
Classifier: Programming Language :: Python :: 3.3
Classifier: Programming Language :: Python :: 3.4
Classifier: Programming Language :: Python :: 3.5
Classifier: Programming Language :: Python :: 3.6
Classifier: Programming Language :: Python :: Implementation :: CPython
Classifier: Programming Language :: Python :: Implementation :: PyPy
Requires-Dist: hypothesis (>=3.8)
Requires-Dist: six (>=1.10)
